mashiro/__init__.py
mashiro/__version__.py
mashiro/core.py
mashiro/data/Sakurasou.list
mashiro-0.2.1.dist-info/LICENSE
mashiro-0.2.1.dist-info/METADATA
mashiro-0.2.1.dist-info/WHEEL
mashiro-0.2.1.dist-info/top_level.txt
mashiro-0.2.1.dist-info/RECORD
