Metadata-Version: 2.1
Name: mashiro
Version: 0.2.1
Summary: ねぇ、君は何色になりたい？（呐，你想变成什么颜色的？）
Home-page: https://github.com/Clancy6/mashiro
Author: Clancy Wang
Author-email: cl@pximg.org
License: MIT
Platform: UNKNOWN
Classifier: License :: OSI Approved :: MIT License
Classifier: Programming Language :: Python
Classifier: Programming Language :: Python :: 3
Classifier: Programming Language :: Python :: 3.6
Classifier: Programming Language :: Python :: Implementation :: CPython
Classifier: Programming Language :: Python :: Implementation :: PyPy
Requires-Python: >=3.0.0
Requires-Dist: requests
